nbfixme.py
nbfixme-0.0.1.dist-info/METADATA
nbfixme-0.0.1.dist-info/WHEEL
nbfixme-0.0.1.dist-info/entry_points.txt
nbfixme-0.0.1.dist-info/licenses/LICENSE.txt
nbfixme-0.0.1.dist-info/RECORD
