Metadata-Version: 2.1
Name: nbfixme
Version: 0.0.1
Summary: Utility to fix basic notebook validation errors
Project-URL: homepage, https://github.com/furechan/nbfixme
Author-email: furechan <furechan@xsmail.com>
License: MIT
License-File: LICENSE.txt
Keywords: jupyter,nbformat,notebook,utility,validation
Classifier: License :: OSI Approved :: MIT License
Classifier: Programming Language :: Python :: 3
Requires-Python: >=3.8
Requires-Dist: click
Provides-Extra: dev
Requires-Dist: ipykernel; extra == 'dev'
